odoo9_addon_report_xlsx-9.0.1.0.1-py2.7-nspkg.pth
odoo_addons/report_xlsx/__openerp__.py
odoo_addons/report_xlsx/__init__.py
odoo_addons/report_xlsx/README.rst
odoo_addons/report_xlsx/report/report_xlsx.py
odoo_addons/report_xlsx/report/__init__.py
odoo_addons/report_xlsx/models/ir_report.py
odoo_addons/report_xlsx/models/__init__.py
odoo_addons/report_xlsx/i18n/hr.po
odoo_addons/report_xlsx/i18n/de.po
odoo_addons/report_xlsx/static/description/icon.png
odoo9_addon_report_xlsx-9.0.1.0.1.dist-info/top_level.txt
odoo9_addon_report_xlsx-9.0.1.0.1.dist-info/WHEEL
odoo9_addon_report_xlsx-9.0.1.0.1.dist-info/RECORD
odoo9_addon_report_xlsx-9.0.1.0.1.dist-info/metadata.json
odoo9_addon_report_xlsx-9.0.1.0.1.dist-info/DESCRIPTION.rst
odoo9_addon_report_xlsx-9.0.1.0.1.dist-info/METADATA
odoo9_addon_report_xlsx-9.0.1.0.1.dist-info/namespace_packages.txt
