Metadata-Version: 2.0
Name: odoo9-addon-report-xlsx
Version: 9.0.1.0.1
Summary: Base module to create xlsx report
Home-page: http://acsone.eu
Author: UNKNOWN
Author-email: UNKNOWN
License: AGPL-3
Platform: UNKNOWN
Requires-Dist: odoo (<9.1a,>=9.0a)
Requires-Dist: xlsxwriter
Classifier: Programming Language :: Python :: 2.7
Classifier: Framework :: Odoo
Classifier: License :: OSI Approved :: GNU Affero General Public License v3
